{
  "kind": "singleType",
  "collectionName": "about_pages",
  "info": {
    "singularName": "about-page",
    "pluralName": "about-pages",
    "displayName": "About Page",
    "description": "Who We Serve page with hero, values/outcomes section and CTA"
  },
  "options": {
    "draftAndPublish": false
  },
  "pluginOptions": {
    "i18n": {
      "localized": false
    }
  },
  "attributes": {
    "subtitle": {
      "type": "string",
      "default": "WHO WE SERVE"
    },
    "title": {
      "type": "text",
      "default": "Partners in Leadership\nDevelopment"
    },
    "heroDescription": {
      "type": "text",
      "default": "Our work is particularly suited to technically strong leaders whose impact depends on effective communication and presence."
    },
    "audienceList": {
      "type": "text",
      "default": "Corporates and financial institutions\nPublic sector and NGOs\nLeadership teams and executives\nProfessionals and emerging leaders"
    },
    "heroImage": {
      "type": "media",
      "multiple": false,
      "allowedTypes": [
        "images"
      ]
    },
    "valuesSubtitle": {
      "type": "string",
      "default": "STRATEGIC OUTCOMES"
    },
    "valuesTitle": {
      "type": "string",
      "default": "What We Achieve"
    },
    "valuesList": {
      "type": "json",
      "default": [
        { "id": 1, "title": "Leadership Pipeline Development", "description": "Building strong leaders ready to take on greater responsibilities." },
        { "id": 2, "title": "Succession Readiness and Talent Visibility", "description": "Preparing leaders for succession and increasing their visibility within the organization." },
        { "id": 3, "title": "Stakeholder Confidence and Executive Readiness", "description": "Enhancing confidence in stakeholder interactions and executive-level readiness." },
        { "id": 4, "title": "Team Alignment and Performance", "description": "Aligning teams through effective communication and improving overall performance." }
      ]
    },
    "ctaTitle": {
      "type": "string",
      "default": "Ready to Partner?"
    },
    "ctaDescription": {
      "type": "text",
      "default": "If you're developing leaders, strengthening client-facing capability or looking for a speaker, we would be glad to explore how we can support your goals."
    },
    "ctaButtonText": {
      "type": "string",
      "default": "Request a Conversation"
    },
    "contentSections": {
      "type": "dynamiczone",
      "components": [
        "sections.text-card",
        "sections.text-image",
        "sections.number",
        "sections.testimonial"
      ]
    }
  }
}
